LICENSE
MANIFEST.in
README.md
dev-requirements.txt
requirements.txt
setup.cfg
setup.py
test-requirements.txt
influxdb_aio/__init__.py
influxdb_aio/_dataframe_client.py
influxdb_aio/chunked_json.py
influxdb_aio/client.py
influxdb_aio/dataframe_client.py
influxdb_aio/exceptions.py
influxdb_aio/helper.py
influxdb_aio/line_protocol.py
influxdb_aio/resultset.py
influxdb_aio.egg-info/PKG-INFO
influxdb_aio.egg-info/SOURCES.txt
influxdb_aio.egg-info/dependency_links.txt
influxdb_aio.egg-info/requires.txt
influxdb_aio.egg-info/top_level.txt
influxdb_aio/influxdb08/__init__.py
influxdb_aio/influxdb08/chunked_json.py
influxdb_aio/influxdb08/client.py
influxdb_aio/influxdb08/dataframe_client.py
influxdb_aio/influxdb08/helper.py
influxdb_aio/tests/__init__.py
influxdb_aio/tests/chunked_json_test.py
influxdb_aio/tests/client_test.py
influxdb_aio/tests/dataframe_client_test.py
influxdb_aio/tests/helper_test.py
influxdb_aio/tests/misc.py
influxdb_aio/tests/resultset_test.py
influxdb_aio/tests/test_line_protocol.py
influxdb_aio/tests/influxdb08/__init__.py
influxdb_aio/tests/influxdb08/client_test.py
influxdb_aio/tests/influxdb08/dataframe_client_test.py
influxdb_aio/tests/influxdb08/helper_test.py
influxdb_aio/tests/server_tests/__init__.py
influxdb_aio/tests/server_tests/base.py
influxdb_aio/tests/server_tests/client_test_with_server.py
influxdb_aio/tests/server_tests/influxdb_instance.py