Metadata-Version: 2.1
Name: influxdb-aio
Version: 5.3.2
Summary: InfluxDB client, asyncio version
Home-page: https://github.com/xp880906/influxdb-python
Author: BruceX
Author-email: xp880906@gmail.com
License: MIT License
Platform: UNKNOWN
Classifier: Development Status :: 3 - Alpha
Classifier: Intended Audience :: Developers
Classifier: License :: OSI Approved :: MIT License
Classifier: Operating System :: OS Independent
Classifier: Programming Language :: Python
Classifier: Programming Language :: Python :: 3.6
Classifier: Topic :: Software Development :: Libraries
Classifier: Topic :: Software Development :: Libraries :: Python Modules
Requires-Python: >=3.6
Provides-Extra: test
